fair_platform/__init__.py
fair_platform/backend/README.md
fair_platform/backend/__init__.py
fair_platform/backend/alembic/__init__.py
fair_platform/backend/alembic/env.py
fair_platform/backend/alembic/versions/20250818_0001_initial.py
fair_platform/backend/alembic/versions/20250823_0002_add_core_models.py
fair_platform/backend/alembic/versions/20251101_0003_auth_redesign.py
fair_platform/backend/alembic/versions/__init__.py
fair_platform/backend/alembic.ini
fair_platform/backend/api/__init__.py
fair_platform/backend/api/routers/__init__.py
fair_platform/backend/api/routers/artifacts.py
fair_platform/backend/api/routers/assignments.py
fair_platform/backend/api/routers/auth.py
fair_platform/backend/api/routers/courses.py
fair_platform/backend/api/routers/plugins.py
fair_platform/backend/api/routers/sessions.py
fair_platform/backend/api/routers/submission_results.py
fair_platform/backend/api/routers/submissions.py
fair_platform/backend/api/routers/users.py
fair_platform/backend/api/routers/version.py
fair_platform/backend/api/routers/workflows.py
fair_platform/backend/api/schema/__init__.py
fair_platform/backend/api/schema/artifact.py
fair_platform/backend/api/schema/assignment.py
fair_platform/backend/api/schema/course.py
fair_platform/backend/api/schema/plugin.py
fair_platform/backend/api/schema/submission.py
fair_platform/backend/api/schema/submission_result.py
fair_platform/backend/api/schema/submitter.py
fair_platform/backend/api/schema/user.py
fair_platform/backend/api/schema/utils.py
fair_platform/backend/api/schema/workflow.py
fair_platform/backend/api/schema/workflow_run.py
fair_platform/backend/data/__init__.py
fair_platform/backend/data/database.py
fair_platform/backend/data/models/__init__.py
fair_platform/backend/data/models/artifact.py
fair_platform/backend/data/models/assignment.py
fair_platform/backend/data/models/course.py
fair_platform/backend/data/models/plugin.py
fair_platform/backend/data/models/submission.py
fair_platform-0.6.4.dist-info/licenses/LICENSE
fair_platform-0.6.4.dist-info/WHEEL
fair_platform-0.6.4.dist-info/entry_points.txt
fair_platform-0.6.4.dist-info/METADATA
fair_platform-0.6.4.dist-info/RECORD
