Metadata-Version: 2.4
Name: fair-platform
Version: 0.6.4
Summary: Fair Platform - The complete platform with backend, frontend, and CLI
Author: Allan Zapata
Author-email: Allan Zapata <allan.zapata@up.ac.pa>
License-Expression: GPL-3.0-or-later
License-File: LICENSE
Classifier: Programming Language :: Python :: 3
Classifier: Operating System :: OS Independent
Classifier: Development Status :: 1 - Planning
Requires-Dist: appdirs>=1.4.4
Requires-Dist: dotenv>=0.9.9
Requires-Dist: fastapi>=0.122.0
Requires-Dist: httpx>=0.25.0
Requires-Dist: packaging>=23.0
Requires-Dist: pydantic[email]>=2.12.5
Requires-Dist: python-jose>=3.5.0
Requires-Dist: python-multipart>=0.0.20
Requires-Dist: sqlalchemy>=2.0.43
Requires-Dist: typer>=0.17.4
Requires-Dist: uvicorn>=0.35.0
Requires-Dist: websockets>=15.0.1
Requires-Dist: bcrypt>=4.0.0
Requires-Dist: pytest>=8.0.0 ; extra == 'test'
Requires-Dist: pytest-asyncio>=0.21.0 ; extra == 'test'
Requires-Dist: httpx>=0.25.0 ; extra == 'test'
Requires-Dist: pytest-mock>=3.11.0 ; extra == 'test'
Requires-Dist: faker>=19.0.0 ; extra == 'test'
Requires-Dist: ruff>=0.13.2 ; extra == 'test'
Requires-Python: >=3.12
Provides-Extra: test
